cerbere/__init__.py
cerbere/accessor/__init__.py
cerbere/accessor/cdataarray.py
cerbere/accessor/cdataset.py
cerbere/accessor/cerberize.py
cerbere/accessor/matching.py
cerbere/accessor/netcdf.py
cerbere/backend/__init__.py
cerbere/backend/ghrsst.py
cerbere/backend/osisafscatl2.py
cerbere/backend/pytest_backend.py
cerbere/cfconvention.py
cerbere/dataset/__init__.py
cerbere/dataset/dataset.py
cerbere/dataset/field.py
cerbere/dataset/ghrsstncdataset.py
cerbere/dataset/ncdataset.py
cerbere/exceptions.py
cerbere/feature/__init__.py
cerbere/feature/cbasecollection.py
cerbere/feature/cbasefeature.py
cerbere/feature/cdiscretefeature.py
cerbere/feature/cgrid.py
cerbere/feature/cgridtimeseries.py
cerbere/feature/cimage.py
cerbere/feature/cimdcollection.py
cerbere/feature/comdcollection.py
cerbere/feature/cpoint.py
cerbere/feature/cprofile.py
cerbere/feature/cracollection.py
cerbere/feature/cswath.py
cerbere/feature/ctimeseries.py
cerbere/feature/ctimeseriesprofile.py
cerbere/feature/ctrajectory.py
cerbere/feature/ctrajectoryprofile.py
cerbere/feature/feature.py
cerbere/feature/grid.py
cerbere/feature/gridtimeseries.py
cerbere/feature/image.py
cerbere/feature/imdcollection.py
cerbere/feature/omdcollection.py
cerbere/feature/point.py
cerbere/feature/profile.py
cerbere/feature/pytest_cfeature.py
cerbere/feature/swath.py
cerbere/feature/timeseries.py
cerbere/feature/timeseriesprofile.py
cerbere/feature/trajectory.py
cerbere/feature/trajectoryprofile.py
cerbere/helpers.py
cerbere/meta.yaml
cerbere/reader/__init__.py
cerbere/reader/basereader.py
cerbere/reader/ghrsst.py
cerbere/reader/osisafscatl2.py
cerbere/reader/pytest_reader.py
cerbere/share/__init__.py
cerbere/share/default_saving_profile.yaml
cerbere/share/ghrsst_saving_profile.yaml
cerbere-3.0.0.post39.dist-info/LICENSE.txt
cerbere-3.0.0.post39.dist-info/METADATA
cerbere-3.0.0.post39.dist-info/WHEEL
cerbere-3.0.0.post39.dist-info/entry_points.txt
cerbere-3.0.0.post39.dist-info/RECORD
