Metadata-Version: 2.1
Name: cerbere
Version: 3.0.0.post39
Summary: A python API to manipulate spatial and temporal observations, compatible with many existing formats, normalizing and typing the representation of these observations.
License: AOSI Approved :: GNU General Public License v3 (GPLv3)
Keywords: ocean,observation,data,analysis
Author: Jean-François Piollé (Ifremer)
Author-email: jean.francois.piolle@ifremer.fr
Maintainer: Jean-François Piollé (Ifremer)
Maintainer-email: jean.francois.piolle@ifremer.fr
Requires-Python: >=3.10,<4.0
Classifier: Development Status :: 4 - Beta
Classifier: Environment :: Console
Classifier: Intended Audience :: Developers
Classifier: Intended Audience :: Science/Research
Classifier: License :: OSI Approved :: Apache Software License
Classifier: License :: Other/Proprietary License
Classifier: Operating System :: OS Independent
Classifier: Programming Language :: Python :: 3
Classifier: Programming Language :: Python :: 3.10
Classifier: Programming Language :: Python :: 3.11
Classifier: Programming Language :: Python :: 3.12
Classifier: Programming Language :: Python :: 3.6
Classifier: Programming Language :: Python :: 3.7
Classifier: Programming Language :: Python :: 3.8
Requires-Dist: cftime (>=1.6.4,<2.0.0)
Requires-Dist: dask (>=2024.8.2,<2025.0.0)
Requires-Dist: h5netcdf (>=1.3.0,<2.0.0)
Requires-Dist: pyyaml (>=6.0.2,<7.0.0)
Requires-Dist: scipy (>=1.14.1,<2.0.0)
Requires-Dist: shapely (>=2.0.6,<3.0.0)
Requires-Dist: xarray (<=2024.1.1)
